abcli/README.py
abcli/__init__.py
abcli/__main__.py
abcli/config.env
abcli/env.py
abcli/host.py
abcli/logger.py
abcli/sample.env
abcli/.abcli/abcli.sh
abcli/.abcli/abcli/arg.sh
abcli/.abcli/abcli/keyword.sh
abcli/.abcli/bootstrap/dependencies.sh
abcli/.abcli/bootstrap/logging.sh
abcli/.abcli/bootstrap/paths.sh
abcli/.abcli/bootstrap/system.sh
abcli/.abcli/modules/abcli.sh
abcli/.abcli/modules/init.sh
abcli/.abcli/modules/initialize.sh
abcli/.abcli/modules/plugins.sh
abcli/.abcli/modules/terraform.sh
abcli/.abcli/modules/plugins/install.sh
abcli/.abcli/modules/plugins/transform.sh
abcli/.abcli/plugins/GPU.sh
abcli/.abcli/plugins/actions.sh
abcli/.abcli/plugins/alias.sh
abcli/.abcli/plugins/build_README.sh
abcli/.abcli/plugins/conda.sh
abcli/.abcli/plugins/ffmpeg.sh
abcli/.abcli/plugins/git.sh
abcli/.abcli/plugins/install.sh
abcli/.abcli/plugins/instance.sh
abcli/.abcli/plugins/latex.sh
abcli/.abcli/plugins/message.sh
abcli/.abcli/plugins/papertrail.sh
abcli/.abcli/plugins/pip.sh
abcli/.abcli/plugins/pypi.sh
abcli/.abcli/plugins/scp.sh
abcli/.abcli/plugins/screen.sh
abcli/.abcli/plugins/session.sh
abcli/.abcli/plugins/ssh.sh
abcli/.abcli/plugins/ssm.sh
abcli/.abcli/plugins/vscode.sh
abcli/.abcli/plugins/wifi.sh
abcli/.abcli/plugins/conda/create.sh
abcli/.abcli/plugins/conda/exists.sh
abcli/.abcli/plugins/conda/list.sh
abcli/.abcli/plugins/conda/rm.sh
abcli/.abcli/plugins/ffmpeg/install.sh
abcli/.abcli/plugins/git/browse.sh
abcli/.abcli/plugins/git/checkout.sh
abcli/.abcli/plugins/git/clone.sh
abcli/.abcli/plugins/git/create_branch.sh
abcli/.abcli/plugins/git/get_repo_name.sh
abcli/.abcli/plugins/git/increment_version.sh
abcli/.abcli/plugins/git/pull.sh
abcli/.abcli/plugins/git/push.sh
abcli/.abcli/plugins/git/review.sh
abcli/.abcli/plugins/git/rm.sh
abcli/.abcli/plugins/git/status.sh
abcli/.abcli/plugins/git/utils.sh
abcli/.abcli/plugins/instance/from_image.sh
abcli/.abcli/plugins/instance/from_template.sh
abcli/.abcli/plugins/instance/get_ip.sh
abcli-9.572.1.dist-info/METADATA
abcli-9.572.1.dist-info/WHEEL
abcli-9.572.1.dist-info/top_level.txt
abcli-9.572.1.dist-info/RECORD
