Metadata-Version: 2.4
Name: abcli
Version: 9.572.1
Summary: 🪄 A language to speak AI.
Home-page: https://github.com/kamangir/awesome-bash-cli
Author: Arash Abadpour (Kamangir)
Author-email: arash@kamangir.net
License: Public Domain
Classifier: Programming Language :: Python :: 3
Classifier: Programming Language :: Unix Shell
Classifier: License :: Public Domain
Classifier: Operating System :: OS Independent
Requires-Dist: blueness
Requires-Dist: blue-options
Requires-Dist: blue-objects
Requires-Dist: boto3
Dynamic: author
Dynamic: author-email
Dynamic: classifier
Dynamic: description
Dynamic: description-content-type
Dynamic: home-page
Dynamic: license
Dynamic: requires-dist
Dynamic: summary
